{
    "dragAndSort": "Vuta bendera kuipanga",
    "facebookTip": "Maoni",
    "messageTip": "Ujumbe",
    "dragAndSortTip": "Vuta na Panga!",
    "languageTip": "Lugha",
    "backHomeTip": "Rudi Nyumbani",
    "settingTip": "Mipangilio",
    "popupTip": "Fungua Dirisha",
    "selectLanguage": "Chagua Lugha",
    "messageList": "Orodha ya Ujumbe",
    "setting": "Mipangilio",
    "settingText1": "Weka usahihi wa desimali kwa ubadilishaji wa sarafu.",
    "settingText2": "Angalau desimali 2 na za juu 6:",
    "provideCompleteInformation": "Tafadhali toa habari kamili",
    "QuestionsAndSuggestions": "Maswali na Mapendekezo",
    "YourNameandContactInformation": "Jina Lako na Taarifa za Mawasiliano:",
    "YourFeedbackIsVeryImportant": "Maoni yako ni muhimu sana!",
    "YourQuestion": "Swali Lako:",
    "OrYourSuggestion": "Au, Mapendekezo Yako:",
    "FeedbackSuccessful": "Maoni Yalifanikiwa",
    "FeedbackFailedPleaseTryAgain": "Maoni Hayakufanikiwa, Tafadhali Jaribu Tena!",
    "PleaseCheckYourNetwork": "Tafadhali angalia mtandao wako",
    "SelectCurrencyToAddToCalculationList": "Chagua sarafu ya kuongeza kwenye orodha ya hesabu",
    "SearchForCurrencyCountryCode": "Tafuta sarafu/nchi/kificho",
    "ViewSelected": "Angalia Iliyochaguliwa",
    "ViewAll": "Angalia Yote"
  }
  